[
{"category":"pnw","age":7,"q":"What giant, hairy creature is said to hide in Northwest forests?","a":"Bigfoot (Sasquatch)"},
{"category":"pnw","age":7,"q":"What is the tallest mountain in Washington?","a":"Mount Rainier"},
{"category":"pnw","age":7,"q":"What famous Seattle tower was built for the 1962 World's Fair?","a":"The Space Needle"},
{"category":"pnw","age":7,"q":"Which Northwest state is famous for growing potatoes?","a":"Idaho"},
{"category":"pnw","age":7,"q":"What is Oregon's state animal?","a":"The beaver"},
{"category":"pnw","age":7,"q":"What black-and-white whales swim in Puget Sound?","a":"Orcas (killer whales)"},
{"category":"pnw","age":7,"q":"Seattle's NFL football team is called the ___?","a":"Seahawks"},
{"category":"pnw","age":7,"q":"Seattle's hockey team is named after what legendary sea monster?","a":"The Kraken"},
{"category":"pnw","age":7,"q":"Washington is the only state named after what kind of person?","a":"A president — George Washington"},
{"category":"pnw","age":7,"q":"What slimy yellow creature is a beloved Northwest forest mascot?","a":"The banana slug"},
{"category":"pnw","age":7,"q":"What famous Seattle wall is covered in chewed gum?","a":"The Gum Wall, near Pike Place Market"},
{"category":"pnw","age":10,"q":"What is the capital of Washington?","a":"Olympia"},
{"category":"pnw","age":10,"q":"What is the capital of Oregon?","a":"Salem"},
{"category":"pnw","age":10,"q":"What is the capital of Idaho?","a":"Boise"},
{"category":"pnw","age":10,"q":"Which Washington volcano famously erupted in 1980?","a":"Mount St. Helens"},
{"category":"pnw","age":10,"q":"What Oregon lake is the deepest lake in the United States?","a":"Crater Lake"},
{"category":"pnw","age":10,"q":"What big river forms much of the border between Washington and Oregon?","a":"The Columbia River"},
{"category":"pnw","age":10,"q":"What coffee company opened its first store at Seattle's Pike Place Market?","a":"Starbucks"},
{"category":"pnw","age":10,"q":"Seattle's baseball team is called the ___?","a":"Mariners"},
{"category":"pnw","age":10,"q":"Portland's NBA basketball team is called the ___?","a":"Trail Blazers"},
{"category":"pnw","age":10,"q":"What is Washington's state nickname?","a":"The Evergreen State"},
{"category":"pnw","age":10,"q":"What is Seattle's city nickname?","a":"The Emerald City"},
{"category":"pnw","age":10,"q":"At what famous Seattle market do workers throw fish to each other?","a":"Pike Place Market"},
{"category":"pnw","age":10,"q":"What is the tallest mountain in Oregon?","a":"Mount Hood"},
{"category":"pnw","age":10,"q":"What mountain range full of volcanoes runs through Washington and Oregon?","a":"The Cascades"},
{"category":"pnw","age":10,"q":"Which 1985 kids' treasure-hunt movie was filmed in Astoria, Oregon?","a":"The Goonies"},
{"category":"pnw","age":10,"q":"What two explorers reached the Pacific Ocean in 1805 after crossing the Northwest?","a":"Lewis and Clark"},
{"category":"pnw","age":10,"q":"What Shoshone woman helped guide the Lewis and Clark expedition?","a":"Sacagawea"},
{"category":"pnw","age":10,"q":"What pioneer wagon route ended in Oregon's Willamette Valley?","a":"The Oregon Trail"},
{"category":"pnw","age":10,"q":"What troll sculpture hides under a bridge in Seattle's Fremont neighborhood?","a":"The Fremont Troll"},
{"category":"pnw","age":10,"q":"Which company did Bill Gates and Paul Allen start, now headquartered in Redmond?","a":"Microsoft"},
{"category":"pnw","age":10,"q":"Jeff Bezos started which giant company near Seattle in 1994?","a":"Amazon"},
{"category":"pnw","age":10,"q":"Which state grows more apples than any other in the US?","a":"Washington"},
{"category":"pnw","age":10,"q":"What sweet yellow-and-red cherry is named after a Washington mountain?","a":"The Rainier cherry"},
{"category":"pnw","age":10,"q":"Tillamook, Oregon is most famous for making what food?","a":"Cheese (and ice cream)"},
{"category":"pnw","age":10,"q":"Boise State University's football field is famously what color?","a":"Blue"},
{"category":"pnw","age":10,"q":"The Seattle Sounders' biggest soccer rivals are the Portland ___?","a":"Timbers"},
{"category":"pnw","age":10,"q":"What is Oregon's state nickname?","a":"The Beaver State"},
{"category":"pnw","age":10,"q":"What giant sea stack rises out of the water at Cannon Beach, Oregon?","a":"Haystack Rock"},
{"category":"pnw","age":10,"q":"What giant burrowing clam with a funny name lives in Puget Sound mud?","a":"The geoduck (pronounced \"gooey-duck\")"},
{"category":"pnw","age":13,"q":"The Twilight books are set in which rainy Washington town?","a":"Forks"},
{"category":"pnw","age":13,"q":"Which legendary guitarist, born in Seattle, headlined Woodstock in 1969?","a":"Jimi Hendrix"},
{"category":"pnw","age":13,"q":"What style of rock music made famous by Nirvana and Pearl Jam came out of Seattle?","a":"Grunge"},
{"category":"pnw","age":13,"q":"Who was the lead singer of Nirvana?","a":"Kurt Cobain"},
{"category":"pnw","age":13,"q":"Seattle is named after a chief of which two Native peoples?","a":"The Duwamish and Suquamish (Chief Seattle)"},
{"category":"pnw","age":13,"q":"Which state runs the largest ferry system in the United States?","a":"Washington"},
{"category":"pnw","age":13,"q":"What is the deepest river gorge in North America, on the Idaho-Oregon border?","a":"Hells Canyon"},
{"category":"pnw","age":13,"q":"What river carved Hells Canyon?","a":"The Snake River"},
{"category":"pnw","age":13,"q":"Boeing's airplane factory in Everett, Washington holds what world record?","a":"It's the largest building in the world by volume"},
{"category":"pnw","age":13,"q":"Nike is headquartered just outside which Oregon city?","a":"Portland (in Beaverton)"},
{"category":"pnw","age":13,"q":"What temperate rain forest sits inside Olympic National Park?","a":"The Hoh Rain Forest"},
{"category":"pnw","age":13,"q":"What Portland shop is famous for its weird and wonderful doughnuts?","a":"Voodoo Doughnut"},
{"category":"pnw","age":13,"q":"Powell's in Portland is the world's largest independent what?","a":"Bookstore"},
{"category":"pnw","age":13,"q":"Spokane's Gonzaga University is nationally famous for which sport?","a":"Basketball"},
{"category":"pnw","age":13,"q":"What is the UW Huskies vs WSU Cougars football rivalry game called?","a":"The Apple Cup"},
{"category":"pnw","age":13,"q":"Which Seattle team won Super Bowl XLVIII in February 2014?","a":"The Seahawks"},
{"category":"pnw","age":13,"q":"Sue Bird won four WNBA championships with which Seattle team?","a":"The Storm"},
{"category":"pnw","age":13,"q":"What was Seattle's NBA team called before it moved to Oklahoma City in 2008?","a":"The SuperSonics"},
{"category":"pnw","age":13,"q":"Multnomah Falls, Oregon's tallest waterfall, pours into which scenic river gorge?","a":"The Columbia River Gorge"},
{"category":"pnw","age":13,"q":"What Bavarian-style alpine village sits in Washington's Cascade mountains?","a":"Leavenworth"},
{"category":"pnw","age":13,"q":"In Oregon, all 363 miles of what are open to the public by law?","a":"The coastline — every beach is public"},
{"category":"pnw","age":13,"q":"What island sits in the middle of Crater Lake?","a":"Wizard Island"},
{"category":"pnw","age":13,"q":"Mount Baker set a world record in the winter of 1998-99 for the most what?","a":"Snowfall in one season — 1,140 inches (95 feet)"},
{"category":"pnw","age":13,"q":"What is the largest species of Pacific salmon?","a":"The Chinook, also called the king salmon"},
{"category":"pnw","age":13,"q":"Which long-running medical drama is set at a fictional Seattle hospital?","a":"Grey's Anatomy"},
{"category":"pnw","age":13,"q":"Keiko, the orca star of Free Willy, lived at an aquarium in which Oregon coast town?","a":"Newport (Oregon Coast Aquarium)"},
{"category":"pnw","age":13,"q":"Lake Washington's Highway 520 bridge holds what world record?","a":"Longest floating bridge in the world"},
{"category":"pnw","age":13,"q":"Which Seattle rapper made \"Thrift Shop\" a #1 hit?","a":"Macklemore"},
{"category":"pnw","age":13,"q":"What's the nickname for Portland's NBA fan base and arena scene?","a":"Rip City"},
{"category":"pnw","age":16,"q":"Starbucks is named after a character from which classic novel?","a":"Moby-Dick — Starbuck was the first mate"},
{"category":"pnw","age":16,"q":"Oregon's Willamette Valley is world-famous for which wine grape?","a":"Pinot noir"},
{"category":"pnw","age":16,"q":"Crater Lake formed when which ancient volcano collapsed about 7,700 years ago?","a":"Mount Mazama"},
{"category":"pnw","age":16,"q":"Which sitcom about a Seattle radio psychiatrist won a record pile of Emmys?","a":"Frasier"},
{"category":"pnw","age":16,"q":"Which sketch comedy show lovingly mocked Portland's quirks?","a":"Portlandia"},
{"category":"pnw","age":16,"q":"Snoqualmie Falls appeared in the opening credits of which cult 1990s TV series?","a":"Twin Peaks"},
{"category":"pnw","age":16,"q":"Tom Hanks and Meg Ryan starred in which 1993 romance set on Lake Union?","a":"Sleepless in Seattle"},
{"category":"pnw","age":16,"q":"The world's first chairlift was built in 1936 at which Idaho ski resort?","a":"Sun Valley"},
{"category":"pnw","age":16,"q":"What is the name of the inland sea shared by Washington and British Columbia?","a":"The Salish Sea"},
{"category":"pnw","age":16,"q":"Which Mariners outfielder set the single-season hits record with 262 in 2004?","a":"Ichiro Suzuki"},
{"category":"pnw","age":16,"q":"Which Mariners legend was nicknamed \"The Kid\"?","a":"Ken Griffey Jr."}
]
